oh_my_env/__init__.py
oh_my_env/backends.py
oh_my_env/base.py
oh_my_env/utils.py
oh_my_env-2.0.0.dist-info/LICENSE
oh_my_env-2.0.0.dist-info/METADATA
oh_my_env-2.0.0.dist-info/WHEEL
oh_my_env-2.0.0.dist-info/entry_points.txt
oh_my_env-2.0.0.dist-info/top_level.txt
oh_my_env-2.0.0.dist-info/RECORD
