Metadata-Version: 2.1
Name: oh-my-env
Version: 2.0.0
Summary: UNKNOWN
Home-page: UNKNOWN
Author: torpedoallen
Author-email: torpedoallen@gmail.com
License: UNKNOWN
Platform: UNKNOWN
Classifier: Programming Language :: Python
Classifier: Programming Language :: Python :: 3
Classifier: Programming Language :: Python :: 3.7
Classifier: Programming Language :: Python :: Implementation :: CPython
Classifier: Programming Language :: Python :: Implementation :: PyPy
Requires-Dist: envparse (==0.2.0)
Requires-Dist: cryptography (==3.0.0)
Requires-Dist: ujson (>=3.0.0)
Requires-Dist: six (>=1.11.0)
Requires-Dist: pytest (<5.0.0)
Provides-Extra: testing
Requires-Dist: pytest ; extra == 'testing'
